ndarrayarray/__init__.py
ndarrayarray/_version.py
ndarrayarray/ndarrayarray.py
ndarrayarray/readcode.py
ndarrayarray-0.1.0.dist-info/METADATA
ndarrayarray-0.1.0.dist-info/WHEEL
ndarrayarray-0.1.0.dist-info/top_level.txt
ndarrayarray-0.1.0.dist-info/RECORD
