Metadata-Version: 2.1
Name: ndarrayarray
Version: 0.1.0
Summary: A memory-mapped array of arbitrarily shaped numpy ndarrays.
Home-page: 
Author: Gabriel Beckers
Author-email: gabriel@gbeckers.nl
License: UNKNOWN
Platform: UNKNOWN
Requires-Dist: darr
